videodrone/__init__.py
videodrone/utils.py
videodrone/drones/__init__.py
videodrone/drones/bbbmeet_garr_chrome.py
videodrone/drones/edumeet_garr_chrome.py
videodrone/drones/jitsi_chrome.py
videodrone/drones/lepida_iorestoacasawork_chrome.py
videodrone/drones/openmeet_garr_chrome.py
videodrone-0.9.0rc3.data/scripts/videodrone
videodrone-0.9.0rc3.dist-info/LICENSE
videodrone-0.9.0rc3.dist-info/METADATA
videodrone-0.9.0rc3.dist-info/WHEEL
videodrone-0.9.0rc3.dist-info/top_level.txt
videodrone-0.9.0rc3.dist-info/RECORD
