Metadata-Version: 2.1
Name: videodrone
Version: 0.9.0rc3
Summary: WebRTC python unit tests inspired to '80s
Home-page: https://github.com/peppelinux/airdrone
Author: Giuseppe De Marco
Author-email: giuseppe.demarco@unical.it
License: Apache 2.0
Platform: UNKNOWN
Classifier: Development Status :: 5 - Production/Stable
Classifier: License :: OSI Approved :: Apache Software License
Classifier: Programming Language :: Python :: 3.6
Classifier: Programming Language :: Python :: 3.7
Classifier: Programming Language :: Python :: 3.8
Requires-Dist: selenium (>=3.0.0)
